selenium_crawler/__init__.py
selenium_crawler/scraping_tools.py
selenium_crawler/webdrivercreator.py
selenium_crawler-0.1.0.dist-info/licenses/LICENSE
tests/__init__.py
tests/test_integration_scraping_tools.py
tests/test_webdrivercreator.py
selenium_crawler-0.1.0.dist-info/METADATA
selenium_crawler-0.1.0.dist-info/WHEEL
selenium_crawler-0.1.0.dist-info/top_level.txt
selenium_crawler-0.1.0.dist-info/RECORD
